apiist/__init__.py
apiist/__main__.py
apiist/action_plugins.py
apiist/csv.py
apiist/http.py
apiist/loadgen.py
apiist/pytest_plugin.py
apiist/samples.py
apiist/ssl_adapter.py
apiist/store.py
apiist/thread.py
apiist/utilities.py
apiist/utils.py
octogaming_apiist-1.0.1.dist-info/LICENSE
octogaming_apiist-1.0.1.dist-info/METADATA
octogaming_apiist-1.0.1.dist-info/WHEEL
octogaming_apiist-1.0.1.dist-info/entry_points.txt
octogaming_apiist-1.0.1.dist-info/top_level.txt
octogaming_apiist-1.0.1.dist-info/RECORD
