Metadata-Version: 2.1
Name: octogaming-apiist
Version: 1.0.1
Summary: Python framework for API testing
Home-page: https://github.com/BetOnYou/apiist
Download-URL: https://github.com/BetOnYou/apiist
Author: Titouan FREVILLE
Author-email: titouan@bet-on-you.com
License: Apache 2.0
License-File: LICENSE
Requires-Dist: nose2
Requires-Dist: chardet
Requires-Dist: requests
Requires-Dist: jsonpath-ng
Requires-Dist: lxml
Requires-Dist: unicodecsv
Requires-Dist: cssselect
Requires-Dist: pyopenssl
Provides-Extra: pytest
Requires-Dist: pytest ; extra == 'pytest'
